patchpatrol/__init__.py
patchpatrol/_version.py
patchpatrol/cli.py
patchpatrol/models.py
patchpatrol/prompts.py
patchpatrol/py.typed
patchpatrol/backends/__init__.py
patchpatrol/backends/base.py
patchpatrol/backends/gemini_backend.py
patchpatrol/backends/llama_backend.py
patchpatrol/backends/onnx_backend.py
patchpatrol/utils/__init__.py
patchpatrol/utils/git_utils.py
patchpatrol/utils/parsing.py
patchpatrol-0.5.0.dist-info/METADATA
patchpatrol-0.5.0.dist-info/WHEEL
patchpatrol-0.5.0.dist-info/entry_points.txt
patchpatrol-0.5.0.dist-info/licenses/LICENSE
patchpatrol-0.5.0.dist-info/RECORD
