Metadata-Version: 2.4
Name: patchpatrol
Version: 0.5.0
Summary: AI-powered commit review system for pre-commit hooks - Local (ONNX/llama.cpp) or cloud (Gemini) analysis of Git commits
Project-URL: Homepage, https://github.com/4383/patchpatrol
Project-URL: Repository, https://github.com/4383/patchpatrol
Project-URL: Issues, https://github.com/4383/patchpatrol/issues
Project-URL: Documentation, https://github.com/4383/patchpatrol/blob/main/README.md
Author-email: Hervé Beraud <herveberaud.pro@gmail.com>
License-Expression: MIT
License-File: LICENSE
Keywords: ai,cloud,code-review,gemini,git,llama-cpp,local,onnx,pre-commit
Classifier: Development Status :: 4 - Beta
Classifier: Environment :: Console
Classifier: Intended Audience :: Developers
Classifier: Operating System :: OS Independent
Classifier: Programming Language :: Python :: 3
Classifier: Programming Language :: Python :: 3.10
Classifier: Programming Language :: Python :: 3.11
Classifier: Programming Language :: Python :: 3.12
Classifier: Programming Language :: Python :: 3.13
Classifier: Topic :: Software Development :: Quality Assurance
Classifier: Topic :: Software Development :: Version Control :: Git
Requires-Python: >=3.10
Requires-Dist: click>=8.0.0
Requires-Dist: gitpython>=3.1.30
Requires-Dist: rich>=13.0.0
Provides-Extra: all
Requires-Dist: google-generativeai>=0.3.0; extra == 'all'
Requires-Dist: llama-cpp-python>=0.2.0; extra == 'all'
Requires-Dist: optimum[onnxruntime]>=1.13.0; extra == 'all'
Requires-Dist: transformers>=4.30.0; extra == 'all'
Provides-Extra: dev
Requires-Dist: black>=23.0.0; extra == 'dev'
Requires-Dist: isort>=5.12.0; extra == 'dev'
Requires-Dist: mypy>=1.0.0; extra == 'dev'
Requires-Dist: pre-commit>=3.0.0; extra == 'dev'
Requires-Dist: pytest-cov>=4.0.0; extra == 'dev'
Requires-Dist: pytest-mock>=3.10.0; extra == 'dev'
Requires-Dist: pytest-xdist>=3.0.0; extra == 'dev'
Requires-Dist: pytest>=7.0.0; extra == 'dev'
Requires-Dist: ruff>=0.1.0; extra == 'dev'
Requires-Dist: tox>=4.0.0; extra == 'dev'
Provides-Extra: gemini
Requires-Dist: google-generativeai>=0.3.0; extra == 'gemini'
Provides-Extra: llama
Requires-Dist: llama-cpp-python>=0.2.0; extra == 'llama'
Provides-Extra: onnx
Requires-Dist: optimum[onnxruntime]>=1.13.0; extra == 'onnx'
Requires-Dist: transformers>=4.30.0; extra == 'onnx'
Provides-Extra: test
Requires-Dist: pytest-cov>=4.0.0; extra == 'test'
Requires-Dist: pytest-mock>=3.10.0; extra == 'test'
Requires-Dist: pytest-xdist>=3.0.0; extra == 'test'
Requires-Dist: pytest>=7.0.0; extra == 'test'
Requires-Dist: tox>=4.0.0; extra == 'test'
